odpslides
