Metadata-Version: 1.1
Name: odpslides
Version: 0.0.3
Summary: Creates OpenDocument Presentations for Microsoft PowerPoint, LibreOffice and OpenOffice
Home-page: http://odpslides.readthedocs.org/en/latest/
Author: Charlie Taylor
Author-email: cet@appliedpython.com
License: GPL-3
Download-URL: https://github.com/sonofeft/ODPSlides
Keywords: odpslides setuptools development
Platform: any
Classifier: Development Status :: 4 - Beta
Classifier: Operating System :: OS Independent
Classifier: Intended Audience :: Developers
Classifier: Intended Audience :: End Users/Desktop
Classifier: Topic :: Software Development :: Build Tools
Classifier: License :: OSI Approved :: GNU General Public License v3 (GPLv3)
Classifier: Programming Language :: Python :: 2
Classifier: Programming Language :: Python :: 2.6
Classifier: Programming Language :: Python :: 2.7
Classifier: Programming Language :: Python :: 3
Classifier: Programming Language :: Python :: 3.2
Classifier: Programming Language :: Python :: 3.3
Classifier: Programming Language :: Python :: 3.4
